[
    {
        "title": "2026 Alan Jay Automotive Network 120 at Sebring International Raceway",
        "url": "https://d1a5pof9bie5vb.cloudfront.net/2026/PROD_WORLDDIRTY_RACE_SEBRING_20MAR2026_IMPC/master.m3u8"
    },
    {
        "title": "Part 2 \u2013 2026 Rolex 24 At Daytona",
        "url": "https://d1a5pof9bie5vb.cloudfront.net/2026/PROD_WORLDDIRTY_RACE_DAYTONA_24JAN2026_IWSC_S002/master.m3u8"
    },
    {
        "title": "Part 6 \u2013 2026 Rolex 24 At Daytona",
        "url": "https://d1a5pof9bie5vb.cloudfront.net/2026/PROD_WORLDDIRTY_RACE_DAYTONA_25JAN2026_IWSC_S006/master.m3u8"
    },
    {
        "title": "Race 1 \u2013 2026 Porsche Carrera Cup at Sebring International Raceway",
        "url": "https://d1a5pof9bie5vb.cloudfront.net/2026/PROD_WORLDDIRTY_RACE_SEBRING_19MAR2026_PCC/master.m3u8"
    },
    {
        "title": "Race 2 \u2013 2026 Porsche Carrera Cup at Sebring International Raceway",
        "url": "https://d1a5pof9bie5vb.cloudfront.net/2026/PROD_WORLDDIRTY_RACE_SEBRING_20MAR2026_PCC/master.m3u8"
    }
]